.gitlab-ci.yml
README.md
setup.py
./lbdevmanager/schema.yaml
bin/lbGetPackagesFromYAML
bin/lbdevcheck
lbdevmanager/CIManager.py
lbdevmanager/GitManager.py
lbdevmanager/LbDevManager.py
lbdevmanager/LbInstallManager.py
lbdevmanager/YamlManager.py
lbdevmanager/__init__.py
lbdevmanager/cvmfs-script.py
lbdevmanager/schema.yaml
lbdevmanager.egg-info/PKG-INFO
lbdevmanager.egg-info/SOURCES.txt
lbdevmanager.egg-info/dependency_links.txt
lbdevmanager.egg-info/requires.txt
lbdevmanager.egg-info/top_level.txt
tests/testInstall.py