Metadata-Version: 1.1
Name: lbdevmanager
Version: 1.0.1
Summary: Tool to manage the LHCb DEV installation on CVMFS
Home-page: https://gitlab.cern.ch/lhcb-core/lbdevmanager
Author: CERN - LHCb Core Software
Author-email: lhcb-core-soft@cern.ch
License: GPL
Keywords: LHCb
Platform: UNKNOWN
Classifier: Development Status :: 3 - Alpha
Classifier: License :: OSI Approved :: GNU General Public License v3 (GPLv3)
Classifier: Programming Language :: Python :: 2.7
Classifier: Programming Language :: Python :: 3.6
Classifier: Programming Language :: Python :: 3.7
